addok_france/__init__.py
addok_france/utils.py
addok_france-1.1.3.dist-info/LICENSE
addok_france-1.1.3.dist-info/METADATA
addok_france-1.1.3.dist-info/WHEEL
addok_france-1.1.3.dist-info/entry_points.txt
addok_france-1.1.3.dist-info/top_level.txt
addok_france-1.1.3.dist-info/RECORD
