Metadata-Version: 2.1
Name: addok-france
Version: 1.1.3
Summary: Add France specific string processors.
Home-page: https://github.com/etalab/addok-france
Author: Yohan Boniface
Author-email: yohan.boniface@data.gouv.fr
License: WTFPL
Keywords: addok geocoding france plugin
Classifier: Development Status :: 5 - Production/Stable
Classifier: Intended Audience :: Developers
Classifier: Topic :: Scientific/Engineering :: GIS
Classifier: Programming Language :: Python :: 3
Classifier: Programming Language :: Python :: 3.4
Classifier: Programming Language :: Python :: 3.5
Classifier: Programming Language :: Python :: 3.6
License-File: LICENSE
Requires-Dist: addok
Provides-Extra: test
Requires-Dist: pytest ; extra == 'test'
